{
  "name": "User adapter delete user",
  "app": "friday-api",
  "language": {
    "name": "java",
    "version": "17.0.8+7-LTS",
    "engine": "OpenJDK 64-Bit Server VM"
  },
  "client": {
    "name": "appmap-java",
    "url": "https://github.com/appland/appmap-java"
  },
  "recorder": {
    "name": "junit",
    "type": "tests"
  },
  "recording": {
    "defined_class": "com.miniyus.friday.integration.users.adapter.out.persistence.UserAdapterTest",
    "method_id": "deleteUser"
  },
  "source_location": "com/miniyus/friday/integration/users/adapter/out/persistence/UserAdapterTest.java:136",
  "framework": {},
  "test_status": "succeeded"
}